{"1":[[{"t":"وَ","g":"P","l":"و","f":["P","PREF"]},{"t":"ٱل","g":"P","l":"ال","f":["DET","PREF"]},{"t":"سَّمَآءِ","g":"N","r":"سمو","l":"سَماء","f":["F","GEN"]}],[{"t":"وَ","g":"P","l":"و","f":["CONJ","PREF"]},{"t":"ٱل","g":"P","l":"ال","f":["DET","PREF"]},{"t":"طَّارِقِ","g":"N","r":"طرق","l":"طارِق","f":["ACT_PCPL","VF:1","M","GEN"]}]],"2":[[{"t":"وَ","g":"P","l":"و","f":["CONJ","PREF"]},{"t":"مَآ","g":"N","l":"ما","f":["INTG"]}],[{"t":"أَدْرَىٰ","g":"V","r":"دري","l":"أَدْرَى","f":["PERF","VF:4","3MS"]},{"t":"كَ","g":"N","f":["PRON","SUFF","2MS"]}],[{"t":"مَا","g":"N","l":"ما","f":["INTG"]}],[{"t":"ٱل","g":"P","l":"ال","f":["DET","PREF"]},{"t":"طَّارِقُ","g":"N","r":"طرق","l":"طارِق","f":["ACT_PCPL","VF:1","M","NOM"]}]],"3":[[{"t":"ٱل","g":"P","l":"ال","f":["DET","PREF"]},{"t":"نَّجْمُ","g":"N","r":"نجم","l":"نَجْم","f":["M","NOM"]}],[{"t":"ٱل","g":"P","l":"ال","f":["DET","PREF"]},{"t":"ثَّاقِبُ","g":"N","r":"ثقب","l":"ثاقِب","f":["ACT_PCPL","VF:1","M","NOM","ADJ"]}]],"4":[[{"t":"إِن","g":"P","l":"إِن","f":["NEG"]}],[{"t":"كُلُّ","g":"N","r":"كلل","l":"كُلّ","f":["M","NOM"]}],[{"t":"نَفْسٍ","g":"N","r":"نفس","l":"نَفْس","f":["FS","INDEF","GEN"]}],[{"t":"لَّمَّا","g":"P","l":"لَمّا","f":["EXP"]}],[{"t":"عَلَيْ","g":"P","l":"عَلَى","f":["P"]},{"t":"هَا","g":"N","f":["PRON","SUFF","3FS"]}],[{"t":"حَافِظٌ","g":"N","r":"حفظ","l":"حافِظ","f":["ACT_PCPL","VF:1","M","INDEF","NOM"]}]],"5":[[{"t":"فَ","g":"P","l":"ف","f":["CONJ","PREF"]},{"t":"لْ","g":"P","l":"ل","f":["IMPV","PREF"]},{"t":"يَنظُرِ","g":"V","r":"نظر","l":"نَظَرَ","f":["IMPF","VF:1","3MS","MOOD:JUS"]}],[{"t":"ٱلْ","g":"P","l":"ال","f":["DET","PREF"]},{"t":"إِنسَٰنُ","g":"N","r":"أنس","l":"إِنسان","f":["M","NOM"]}],[{"t":"مِ","g":"P","l":"مِن","f":["P"]},{"t":"مَّ","g":"N","l":"ما","f":["REL"]}],[{"t":"خُلِقَ","g":"V","r":"خلق","l":"خَلَقَ","f":["PERF","VF:1","PASS","3MS"]}]],"6":[[{"t":"خُلِقَ","g":"V","r":"خلق","l":"خَلَقَ","f":["PERF","VF:1","PASS","3MS"]}],[{"t":"مِن","g":"P","l":"مِن","f":["P"]}],[{"t":"مَّآءٍ","g":"N","r":"موه","l":"ماء","f":["M","INDEF","GEN"]}],[{"t":"دَافِقٍ","g":"N","r":"دفق","l":"دافِق","f":["ACT_PCPL","VF:1","M","INDEF","GEN","ADJ"]}]],"7":[[{"t":"يَخْرُجُ","g":"V","r":"خرج","l":"خَرَجَ","f":["IMPF","VF:1","3MS","MOOD:IND"]}],[{"t":"مِنۢ","g":"P","l":"مِن","f":["P"]}],[{"t":"بَيْنِ","g":"N","r":"بين","l":"بَيْن","f":["GEN"]}],[{"t":"ٱل","g":"P","l":"ال","f":["DET","PREF"]},{"t":"صُّلْبِ","g":"N","r":"صلب","l":"صُلْب","f":["M","GEN"]}],[{"t":"وَ","g":"P","l":"و","f":["CONJ","PREF"]},{"t":"ٱل","g":"P","l":"ال","f":["DET","PREF"]},{"t":"تَّرَآئِبِ","g":"N","r":"ترب","l":"تَرائِب","f":["MP","GEN"]}]],"8":[[{"t":"إِنَّ","g":"P","l":"إِنّ","f":["ACC","FAM:إِنّ"]},{"t":"هُۥ","g":"N","f":["PRON","SUFF","3MS"]}],[{"t":"عَلَىٰ","g":"P","l":"عَلَى","f":["P"]}],[{"t":"رَجْعِ","g":"N","r":"رجع","l":"رَجْع","f":["M","GEN"]},{"t":"هِۦ","g":"N","f":["PRON","SUFF","3MS"]}],[{"t":"لَ","g":"P","l":"ل","f":["EMPH","PREF"]},{"t":"قَادِرٌ","g":"N","r":"قدر","l":"قادِر","f":["ACT_PCPL","VF:1","M","INDEF","NOM"]}]],"9":[[{"t":"يَوْمَ","g":"N","r":"يوم","l":"يَوْم","f":["T","M","ACC"]}],[{"t":"تُبْلَى","g":"V","r":"بلو","l":"بَلَوْ","f":["IMPF","VF:1","PASS","3FS","MOOD:IND"]}],[{"t":"ٱل","g":"P","l":"ال","f":["DET","PREF"]},{"t":"سَّرَآئِرُ","g":"N","r":"سرر","l":"سَرائِر","f":["FP","NOM"]}]],"10":[[{"t":"فَ","g":"P","l":"ف","f":["CONJ","PREF"]},{"t":"مَا","g":"P","l":"ما","f":["NEG"]}],[{"t":"لَ","g":"P","l":"ل","f":["P","PREF"]},{"t":"هُۥ","g":"N","f":["PRON","3MS"]}],[{"t":"مِن","g":"P","l":"مِن","f":["P"]}],[{"t":"قُوَّةٍ","g":"N","r":"قوي","l":"قُوَّة","f":["F","INDEF","GEN"]}],[{"t":"وَ","g":"P","l":"و","f":["CONJ","PREF"]},{"t":"لَا","g":"P","l":"لا","f":["NEG"]}],[{"t":"نَاصِرٍ","g":"N","r":"نصر","l":"ناصِر","f":["ACT_PCPL","VF:1","M","INDEF","GEN"]}]],"11":[[{"t":"وَ","g":"P","l":"و","f":["P","PREF"]},{"t":"ٱل","g":"P","l":"ال","f":["DET","PREF"]},{"t":"سَّمَآءِ","g":"N","r":"سمو","l":"سَماء","f":["F","GEN"]}],[{"t":"ذَاتِ","g":"N","l":"ذُو","f":["FS","GEN"]}],[{"t":"ٱل","g":"P","l":"ال","f":["DET","PREF"]},{"t":"رَّجْعِ","g":"N","r":"رجع","l":"رَجْع","f":["M","GEN"]}]],"12":[[{"t":"وَ","g":"P","l":"و","f":["CONJ","PREF"]},{"t":"ٱلْ","g":"P","l":"ال","f":["DET","PREF"]},{"t":"أَرْضِ","g":"N","r":"أرض","l":"أَرْض","f":["F","GEN"]}],[{"t":"ذَاتِ","g":"N","l":"ذُو","f":["FS","GEN"]}],[{"t":"ٱل","g":"P","l":"ال","f":["DET","PREF"]},{"t":"صَّدْعِ","g":"N","r":"صدع","l":"صَدْع","f":["M","GEN"]}]],"13":[[{"t":"إِنَّ","g":"P","l":"إِنّ","f":["ACC","FAM:إِنّ"]},{"t":"هُۥ","g":"N","f":["PRON","SUFF","3MS"]}],[{"t":"لَ","g":"P","l":"ل","f":["EMPH","PREF"]},{"t":"قَوْلٌ","g":"N","r":"قول","l":"قَوْل","f":["VN","VF:1","M","INDEF","NOM"]}],[{"t":"فَصْلٌ","g":"N","r":"فصل","l":"فَصْل","f":["M","INDEF","NOM","ADJ"]}]],"14":[[{"t":"وَ","g":"P","l":"و","f":["CONJ","PREF"]},{"t":"مَا","g":"P","l":"ما","f":["NEG","FAM:كَان"]}],[{"t":"هُوَ","g":"N","f":["PRON","3MS"]}],[{"t":"بِ","g":"P","l":"ب","f":["P","PREF"]},{"t":"ٱلْ","g":"P","l":"ال","f":["DET","PREF"]},{"t":"هَزْلِ","g":"N","r":"هزل","l":"هَزْل","f":["M","GEN"]}]],"15":[[{"t":"إِنَّ","g":"P","l":"إِنّ","f":["ACC","FAM:إِنّ"]},{"t":"هُمْ","g":"N","f":["PRON","SUFF","3MP"]}],[{"t":"يَكِيدُ","g":"V","r":"كيد","l":"كِيدُ","f":["IMPF","VF:1","3MP","MOOD:IND"]},{"t":"ونَ","g":"N","f":["PRON","SUFF","3MP"]}],[{"t":"كَيْدًا","g":"N","r":"كيد","l":"كَيْد","f":["M","INDEF","ACC"]}]],"16":[[{"t":"وَ","g":"P","l":"و","f":["CONJ","PREF"]},{"t":"أَكِيدُ","g":"V","r":"كيد","l":"كِيدُ","f":["IMPF","VF:1","1S","MOOD:IND"]}],[{"t":"كَيْدًا","g":"N","r":"كيد","l":"كَيْد","f":["M","INDEF","ACC"]}]],"17":[[{"t":"فَ","g":"P","l":"ف","f":["REM","PREF"]},{"t":"مَهِّلِ","g":"V","r":"مهل","l":"مَهِّلِ","f":["IMPV","VF:2","2MS"]}],[{"t":"ٱلْ","g":"P","l":"ال","f":["DET","PREF"]},{"t":"كَٰفِرِينَ","g":"N","r":"كفر","l":"كافِر","f":["ACT_PCPL","VF:1","MP","ACC"]}],[{"t":"أَمْهِلْ","g":"V","r":"مهل","l":"أَمْهِلْ","f":["IMPV","VF:4","2MS"]},{"t":"هُمْ","g":"N","f":["PRON","SUFF","3MP"]}],[{"t":"رُوَيْدًۢا","g":"N","r":"رود","l":"رُوَيْد","f":["M","INDEF","ACC"]}]]}