{"1":[[{"t":"ٱلْ","g":"P","l":"ال","f":["DET","PREF"]},{"t":"قَارِعَةُ","g":"N","r":"قرع","l":"قارِعَة","f":["F","NOM"]}]],"2":[[{"t":"مَا","g":"N","l":"ما","f":["INTG"]}],[{"t":"ٱلْ","g":"P","l":"ال","f":["DET","PREF"]},{"t":"قَارِعَةُ","g":"N","r":"قرع","l":"قارِعَة","f":["F","NOM"]}]],"3":[[{"t":"وَ","g":"P","l":"و","f":["CONJ","PREF"]},{"t":"مَآ","g":"N","l":"ما","f":["INTG"]}],[{"t":"أَدْرَىٰ","g":"V","r":"دري","l":"أَدْرَى","f":["PERF","VF:4","3MS"]},{"t":"كَ","g":"N","f":["PRON","SUFF","2MS"]}],[{"t":"مَا","g":"N","l":"ما","f":["INTG"]}],[{"t":"ٱلْ","g":"P","l":"ال","f":["DET","PREF"]},{"t":"قَارِعَةُ","g":"N","r":"قرع","l":"قارِعَة","f":["F","NOM"]}]],"4":[[{"t":"يَوْمَ","g":"N","r":"يوم","l":"يَوْم","f":["T","M","ACC"]}],[{"t":"يَكُونُ","g":"V","r":"كون","l":"كانَ","f":["IMPF","VF:1","FAM:كَان","3MS","MOOD:IND"]}],[{"t":"ٱل","g":"P","l":"ال","f":["DET","PREF"]},{"t":"نَّاسُ","g":"N","r":"أنس","l":"ناس","f":["MP","NOM"]}],[{"t":"كَ","g":"P","l":"ك","f":["P","PREF"]},{"t":"ٱلْ","g":"P","l":"ال","f":["DET","PREF"]},{"t":"فَرَاشِ","g":"N","r":"فرش","l":"فَراش","f":["M","GEN"]}],[{"t":"ٱلْ","g":"P","l":"ال","f":["DET","PREF"]},{"t":"مَبْثُوثِ","g":"N","r":"بثث","l":"مَبْثُوث","f":["PASS_PCPL","VF:1","M","GEN","ADJ"]}]],"5":[[{"t":"وَ","g":"P","l":"و","f":["CONJ","PREF"]},{"t":"تَكُونُ","g":"V","r":"كون","l":"كانَ","f":["IMPF","VF:1","FAM:كَان","3FS","MOOD:IND"]}],[{"t":"ٱلْ","g":"P","l":"ال","f":["DET","PREF"]},{"t":"جِبَالُ","g":"N","r":"جبل","l":"جَبَل","f":["MP","NOM"]}],[{"t":"كَ","g":"P","l":"ك","f":["P","PREF"]},{"t":"ٱلْ","g":"P","l":"ال","f":["DET","PREF"]},{"t":"عِهْنِ","g":"N","r":"عهن","l":"عِهْن","f":["M","GEN"]}],[{"t":"ٱلْ","g":"P","l":"ال","f":["DET","PREF"]},{"t":"مَنفُوشِ","g":"N","r":"نفش","l":"مَنفُوش","f":["PASS_PCPL","VF:1","M","GEN","ADJ"]}]],"6":[[{"t":"فَ","g":"P","l":"ف","f":["REM","PREF"]},{"t":"أَمَّا","g":"P","l":"أَمّا","f":["EXL"]}],[{"t":"مَن","g":"N","l":"مَن","f":["COND"]}],[{"t":"ثَقُلَتْ","g":"V","r":"ثقل","l":"ثَقُلَتْ","f":["PERF","VF:1","3FS"]}],[{"t":"مَوَٰزِينُ","g":"N","r":"وزن","l":"مِيزان","f":["MP","NOM"]},{"t":"هُۥ","g":"N","f":["PRON","SUFF","3MS"]}]],"7":[[{"t":"فَ","g":"P","l":"ف","f":["RSLT","PREF"]},{"t":"هُوَ","g":"N","f":["PRON","3MS"]}],[{"t":"فِى","g":"P","l":"فِي","f":["P"]}],[{"t":"عِيشَةٍ","g":"N","r":"عيش","l":"عِيشَة","f":["F","INDEF","GEN"]}],[{"t":"رَّاضِيَةٍ","g":"N","r":"رضو","l":"راضِيَة","f":["ACT_PCPL","VF:1","F","INDEF","GEN","ADJ"]}]],"8":[[{"t":"وَ","g":"P","l":"و","f":["CONJ","PREF"]},{"t":"أَمَّا","g":"P","l":"أَمّا","f":["EXL"]}],[{"t":"مَنْ","g":"N","l":"مَن","f":["COND"]}],[{"t":"خَفَّتْ","g":"V","r":"خفف","l":"خَفَّتْ","f":["PERF","VF:1","3FS"]}],[{"t":"مَوَٰزِينُ","g":"N","r":"وزن","l":"مِيزان","f":["MP","NOM"]},{"t":"هُۥ","g":"N","f":["PRON","SUFF","3MS"]}]],"9":[[{"t":"فَ","g":"P","l":"ف","f":["RSLT","PREF"]},{"t":"أُمُّ","g":"N","r":"أمم","l":"أُمّ","f":["FS","NOM"]},{"t":"هُۥ","g":"N","f":["PRON","SUFF","3MS"]}],[{"t":"هَاوِيَةٌ","g":"N","r":"هوي","l":"هاوِيَة","f":["ACT_PCPL","VF:1","F","INDEF","NOM"]}]],"10":[[{"t":"وَ","g":"P","l":"و","f":["CONJ","PREF"]},{"t":"مَآ","g":"N","l":"ما","f":["INTG"]}],[{"t":"أَدْرَىٰ","g":"V","r":"دري","l":"أَدْرَى","f":["PERF","VF:4","3MS"]},{"t":"كَ","g":"N","f":["PRON","SUFF","2MS"]}],[{"t":"مَا","g":"N","l":"ما","f":["INTG"]}],[{"t":"هِيَهْ","g":"N","f":["PRON","3FS"]}]],"11":[[{"t":"نَارٌ","g":"N","r":"نور","l":"نار","f":["F","INDEF","NOM"]}],[{"t":"حَامِيَةٌۢ","g":"N","r":"حمي","l":"حامِيَة","f":["ACT_PCPL","VF:1","F","INDEF","NOM","ADJ"]}]]}